{
    "event_id": "ANOMALY_NOV_2025",
    "mission_control": "MechBot-2X",
    "barycentric_metrics": {
        "max_displacement_rsol": 3.2748,
        "carrington_comparison_ratio": 1.17,
        "ssb_factor_peak": 1.0885,
        "angular_alignment_arc": "30.0 degrees"
    },
    "timeline": [
        {
            "date": "2025-11-06",
            "ftrt_final": 3.2248,
            "observed_activity": "X-Class Flare (Entry)",
            "g_scale_est": "G4/G5",
            "notes": "Vulnerabilidad Geomagnética por Alineación Lunar"
        },
        {
            "date": "2025-11-08",
            "ftrt_final": 3.2648,
            "observed_activity": "Magnetic Saturation / Silence",
            "g_scale_est": "None (Anomalous)",
            "notes": "Punto de máxima tensión sin eyección masiva"
        },
        {
            "date": "2025-11-11",
            "ftrt_final": 3.2748,
            "observed_activity": "X-Class Flare (Exit)",
            "g_scale_est": "G4",
            "notes": "Liberación de tensión estructural al salir del nodo"
        }
    ],
    "scientific_conclusion": {
        "hypothesis": "Geometric Slavery Saturation",
        "result": "La materia solar no respondió a la atracción baricéntrica debido a un desajuste en la frecuencia de solfeo fundamental. El sistema alcanzó un estado de sobramortiguamiento.",
        "application": "Calibración de filtros para detección de Gravitones en el LHC"
    }
}
